{
  "minVersion": "0.1",
  "headerImage": "https://fffdmin.github.io/cydia/sileo/assets/tweetbot.png",
  "tintColor": "#4430D9",
  "tabs": [
    {
      "tabname": "详情",
      "views": [
        {
          "class": "DepictionScreenshotsView",
          "screenshots": [
            {
              "url": "https://fffdmin.github.io/cydia/depictions/cn.fffdmin.tweetbot/screenshots/1.jpg",
              "accessibilityText": "Screenshot"
            },
            {
              "url": "https://fffdmin.github.io/cydia/depictions/cn.fffdmin.tweetbot/screenshots/2.jpg",
              "accessibilityText": "Screenshot"
            },
            {
              "url": "https://fffdmin.github.io/cydia/depictions/cn.fffdmin.tweetbot/screenshots/3.jpg",
              "accessibilityText": "Screenshot"
            },
            {
              "url": "https://fffdmin.github.io/cydia/depictions/cn.fffdmin.tweetbot/screenshots/4.jpg",
              "accessibilityText": "Screenshot"
            }
          ],
          "itemCornerRadius": 8,
          "itemSize": "{185,400}"
        },
        {
          "markdown": "全版本支持，此插件包含繁体&简体中文语言包，无需额外设置安装后根据系统语言自动启用",
          "useSpacing": "true",
          "class": "DepictionMarkdownView"
        },
        {
          "class": "DepictionSpacerView"
        },
        {
          "class": "DepictionHeaderView",
          "title": "更多信息"
        },
        {
          "class": "DepictionTableTextView",
          "title": "开发者",
          "text": "fffdmin"
        },
        {
          "class": "DepictionTableTextView",
          "title": "版本",
          "text": "1.0.3"
        },
        {
          "class": "DepictionTableTextView",
          "title": "兼容性",
          "text": "All"
        },
        {
          "class": "DepictionTableTextView",
          "title": "类型",
          "text": "Localization "
        },
        {
          "class": "DepictionSpacerView"
        },
        {
          "class": "DepictionTableButtonView",
          "title": "技术支持",
          "action": "depiction-https://fffdmin.github.io/cydia/sileo/help.json",
          "openExternal": "true",
          "tintColor": "#573DD9"
        },
        {
          "class": "DepictionLabelView",
          "text": "© 2020 fffdmin ❤",
          "textColor": "#999999",
          "fontSize": "10.0",
          "alignment": 1
        }
      ],
      "class": "DepictionStackView"
    },
    {
      "tabname": "更新日志",
      "views": [
        {
          "class": "DepictionMarkdownView",
          "markdown": "### 5.2.0\n- 添加了一些字符串\n-更新了 3D-Touch 菜单 "
        },
        {
          "class": "DepictionMarkdownView",
          "markdown": "### 5.14\n- 首次更新 "
        },
        {
          "class": "DepictionLabelView",
          "text": "© 2020 fffdmin ❤",
          "textColor": "#999999",
          "fontSize": "10.0",
          "alignment": 1
        }
      ],
      "class": "DepictionStackView"
    }
  ],
  "class": "DepictionTabView"
}
